TkAccessory/Loading.py
TkAccessory/Progress.py
TkAccessory/__init__.py
tkaccessory-0.0.1.dist-info/METADATA
tkaccessory-0.0.1.dist-info/WHEEL
tkaccessory-0.0.1.dist-info/top_level.txt
tkaccessory-0.0.1.dist-info/RECORD
