Metadata-Version: 2.4
Name: TkAccessory
Version: 0.0.1
Summary: GUI Tool kit
Author: Seyed Moied Seyedi (Single Star)
License: MIT
Requires-Dist: customtkinter
Dynamic: author
Dynamic: description
Dynamic: description-content-type
Dynamic: license
Dynamic: requires-dist
Dynamic: summary
